README.rst
setup.py
poetry/__init__.py
poetry/haiku.py
poetry/data_constructor/__init__.py
poetry/data_constructor/data_constructor.py
poetry/data_constructor/words_data.py
poetry/data_constructor/words_data_constructor.py
poetry/haiker/__init__.py
poetry/haiker/haiker.py
poetry/output/__init__.py
poetry/rhymer/__init__.py
poetry/rhymer/rhymer.py
poetry/utils/__init__.py
poetry/utils/argparsers.py
poetry/utils/data_exporter.py
poetry/utils/data_reader.py
poetry/utils/multi_dimentional_array_encoder.py
rhyme_haiker.egg-info/PKG-INFO
rhyme_haiker.egg-info/SOURCES.txt
rhyme_haiker.egg-info/dependency_links.txt
rhyme_haiker.egg-info/entry_points.txt
rhyme_haiker.egg-info/requires.txt
rhyme_haiker.egg-info/top_level.txt
tests/__init__.py
tests/test_data_constructor.py
tests/test_data_exporter.py
tests/test_haiker.py
tests/test_rhymer.py
tests/test_words_data_constructor.py