Metadata-Version: 1.1
Name: rhyme-haiker
Version: 2.0.6
Summary: A rhyming haiku generator.
Home-page: https://github.com/shitake/rhyme-haiker
Author: pochiyuru
Author-email: pochiyuru@gmail.com
License: MIT
Keywords: rhyme haiku
Platform: UNKNOWN
Classifier: Development Status :: 4 - Beta
Classifier: Intended Audience :: End Users/Desktop
Classifier: Natural Language :: Japanese
Classifier: Programming Language :: Python :: 3.5
Classifier: Topic :: Communications
